mcmahon/__init__.py
mcmahon/constants.py
mcmahon/game.py
mcmahon/helpers.py
mcmahon/parameters.py
mcmahon/participant.py
mcmahon/tournament.py
mcmahon-0.3.0.dist-info/WHEEL
mcmahon-0.3.0.dist-info/METADATA
mcmahon-0.3.0.dist-info/RECORD
