Metadata-Version: 2.1
Name: mcmahon
Version: 0.3.0
Summary: McMahon Tournament Manager
Author: Oleksandr Hiliazov
Author-email: oleksandr.hiliazov@eleks.com
Requires-Python: >=3.8,<3.11
Classifier: Programming Language :: Python :: 3
Classifier: Programming Language :: Python :: 3.10
Classifier: Programming Language :: Python :: 3.8
Classifier: Programming Language :: Python :: 3.9
Requires-Dist: scipy (>=1.7.2,<2.0.0)
